digital_tickler/__init__.py
digital_tickler/_version.py
digital_tickler/digital_tickler.py
digital_tickler-0.0.2.dist-info/LICENSE
digital_tickler-0.0.2.dist-info/METADATA
digital_tickler-0.0.2.dist-info/WHEEL
digital_tickler-0.0.2.dist-info/entry_points.txt
digital_tickler-0.0.2.dist-info/top_level.txt
digital_tickler-0.0.2.dist-info/RECORD
