Metadata-Version: 2.1
Name: digital-tickler
Version: 0.0.2
Summary: Digital tickler activating files or directories on pre-defined dates
Home-page: https://github.com/geritwagner/digital_tickler
Author: Gerit Wagner
Author-email: gerit.wagner@posteo.de
License: MIT license
Keywords: digital_tickler
Platform: UNKNOWN
Classifier: Development Status :: 2 - Pre-Alpha
Classifier: Intended Audience :: Developers
Classifier: License :: OSI Approved :: MIT License
Classifier: Natural Language :: English
Classifier: Programming Language :: Python :: 3
Classifier: Programming Language :: Python :: 3.6
Classifier: Programming Language :: Python :: 3.7
Classifier: Programming Language :: Python :: 3.8
Requires-Python: >=3.6
License-File: LICENSE
Requires-Dist: Click (>=7.0)
